networking_hyperv/__init__.py
networking_hyperv/version.py
networking_hyperv/common/__init__.py
networking_hyperv/common/i18n.py
networking_hyperv/neutron/__init__.py
networking_hyperv/neutron/_common_utils.py
networking_hyperv/neutron/config.py
networking_hyperv/neutron/constants.py
networking_hyperv/neutron/exception.py
networking_hyperv/neutron/hyperv_agent_notifier.py
networking_hyperv/neutron/neutron_client.py
networking_hyperv/neutron/nvgre_ops.py
networking_hyperv/neutron/security_groups_driver.py
networking_hyperv/neutron/trunk_driver.py
networking_hyperv/neutron/agent/__init__.py
networking_hyperv/neutron/agent/base.py
networking_hyperv/neutron/agent/hnv_metadata_agent.py
networking_hyperv/neutron/agent/hnv_neutron_agent.py
networking_hyperv/neutron/agent/hyperv_neutron_agent.py
networking_hyperv/neutron/agent/layer2.py
networking_hyperv/neutron/ml2/README
networking_hyperv/neutron/ml2/__init__.py
networking_hyperv/neutron/ml2/mech_hyperv.py
networking_hyperv/neutron/qos/__init__.py
networking_hyperv/neutron/qos/qos_driver.py
networking_hyperv/tests/__init__.py
networking_hyperv/tests/base.py
networking_hyperv/tests/unit/__init__.py
networking_hyperv/tests/unit/neutron/__init__.py
networking_hyperv/tests/unit/neutron/test_common_utils.py
networking_hyperv/tests/unit/neutron/test_config.py
networking_hyperv/tests/unit/neutron/test_hyperv_agent_notifier.py
networking_hyperv/tests/unit/neutron/test_mech_hyperv.py
networking_hyperv/tests/unit/neutron/test_neutron_client.py
networking_hyperv/tests/unit/neutron/test_nvgre_ops.py
networking_hyperv/tests/unit/neutron/test_security_groups_driver.py
networking_hyperv/tests/unit/neutron/test_trunk_driver.py
networking_hyperv/tests/unit/neutron/agent/__init__.py
networking_hyperv/tests/unit/neutron/agent/test_base.py
networking_hyperv/tests/unit/neutron/agent/test_hnv_metadata_agent.py
networking_hyperv/tests/unit/neutron/agent/test_hnv_neutron_agent.py
networking_hyperv-14.0.0.dist-info/AUTHORS
networking_hyperv-14.0.0.dist-info/LICENSE
networking_hyperv-14.0.0.dist-info/METADATA
networking_hyperv-14.0.0.dist-info/WHEEL
networking_hyperv-14.0.0.dist-info/entry_points.txt
networking_hyperv-14.0.0.dist-info/pbr.json
networking_hyperv-14.0.0.dist-info/top_level.txt
networking_hyperv-14.0.0.dist-info/RECORD
