Metadata-Version: 2.1
Name: networking-hyperv
Version: 14.0.0
Summary: This project tracks the work to integrate the Hyper-V networking with Neutron. This project contains the Hyper-V Neutron Agent Mixin, Security Groups Driver, ML2 Mechanism Driver and the utils modules they use in order to properly bind neutron ports on a Hyper-V host. This project resulted from the neutron core vendor decomposition.
Home-page: https://github.com/openstack/networking-hyperv
Author: OpenStack
Author-email: openstack-discuss@lists.openstack.org
License: Apache License, Version 2.0
Keywords: openstack neutron hyper-v networking
Platform: UNKNOWN
Classifier: Environment :: OpenStack
Classifier: Intended Audience :: Information Technology
Classifier: Intended Audience :: System Administrators
Classifier: License :: OSI Approved :: Apache Software License
Classifier: Operating System :: Microsoft :: Windows
Classifier: Programming Language :: Python
Classifier: Programming Language :: Python :: Implementation :: CPython
Classifier: Programming Language :: Python :: 3 :: Only
Classifier: Programming Language :: Python :: 3
Classifier: Programming Language :: Python :: 3.8
Requires-Python: >=3.8
Requires-Dist: eventlet (!=0.18.3,!=0.20.1,>=0.18.2)
Requires-Dist: neutron-lib (>=1.28.0)
Requires-Dist: neutron (>=13.0.0.0b1)
Requires-Dist: os-win (>=3.0.0)
Requires-Dist: oslo.config (>=5.2.0)
Requires-Dist: oslo.i18n (>=3.15.3)
Requires-Dist: oslo.log (>=3.36.0)
Requires-Dist: oslo.serialization (!=2.19.1,>=2.18.0)
Requires-Dist: oslo.utils (>=3.33.0)
Requires-Dist: pbr (!=2.1.0,>=2.0.0)
Requires-Dist: python-neutronclient (>=6.7.0)
